trimmargin/__init__.py
trimmargin/__main__.py
trimmargin/cli.py
trimmargin/core.py
trimmargin/py.typed
trimmargin-1.0.0.dist-info/WHEEL
trimmargin-1.0.0.dist-info/entry_points.txt
trimmargin-1.0.0.dist-info/METADATA
trimmargin-1.0.0.dist-info/RECORD
