Metadata-Version: 2.3
Name: trimmargin
Version: 1.0.0
Summary: Kotlin-style trimMargin utilities for Python, with a tiny CLI.
Keywords: text,strings,indentation,kotlin,trimMargin,cli
Author: Sash Sinha
Author-email: Sash Sinha <sashsinha1@gmail.com>
License: MIT
Classifier: Development Status :: 5 - Production/Stable
Classifier: Intended Audience :: Developers
Classifier: License :: OSI Approved :: MIT License
Classifier: Programming Language :: Python
Classifier: Programming Language :: Python :: 3
Classifier: Programming Language :: Python :: 3.10
Classifier: Programming Language :: Python :: 3.11
Classifier: Programming Language :: Python :: 3.12
Classifier: Programming Language :: Python :: 3.13
Classifier: Typing :: Typed
Requires-Dist: pytest>=8.0 ; extra == 'dev'
Requires-Dist: pytest-cov>=5.0 ; extra == 'dev'
Requires-Dist: ruff>=0.5.0 ; extra == 'dev'
Requires-Dist: mypy>=1.10.0 ; extra == 'dev'
Requires-Python: >=3.10
Project-URL: Homepage, https://github.com/sashsinha/trimmargin
Project-URL: Issues, https://github.com/sashsinha/trimmargin/issues
Provides-Extra: dev
